quickq.py
quickq-17.10.4.dist-info/DESCRIPTION.rst
quickq-17.10.4.dist-info/METADATA
quickq-17.10.4.dist-info/RECORD
quickq-17.10.4.dist-info/WHEEL
quickq-17.10.4.dist-info/metadata.json
quickq-17.10.4.dist-info/top_level.txt
